LICENSE
MANIFEST.in
README.md
pyproject.toml
setup.py
motorcortex/__init__.py
motorcortex/init_threads.py
motorcortex/message_types.py
motorcortex/motorcortex_hash.json
motorcortex/motorcortex_pb2.py
motorcortex/nng_url.py
motorcortex/parameter_tree.py
motorcortex/reply.py
motorcortex/request.py
motorcortex/setup_logger.py
motorcortex/state_callback_handler.py
motorcortex/subscribe.py
motorcortex/subscription.py
motorcortex/timespec.py
motorcortex/version.py
motorcortex_python.egg-info/PKG-INFO
motorcortex_python.egg-info/SOURCES.txt
motorcortex_python.egg-info/dependency_links.txt
motorcortex_python.egg-info/requires.txt
motorcortex_python.egg-info/top_level.txt