Metadata-Version: 2.1
Name: motorcortex-python
Version: 0.25.1
Summary: Python bindings for Motorcortex Engine
Home-page: https://www.motorcortex.io
Author: Alexey Zakharov
Author-email: alexey.zakharov@vectioneer.com
License: MIT
License-File: LICENSE
Requires-Dist: pynng==0.8.*
Requires-Dist: protobuf>=3.20
